Metadata-Version: 2.4
Name: llama-index-embeddings-huggingface-optimum-intel
Version: 0.4.1
Summary: llama-index embeddings Optimum Intel integration
Author-email: Your Name <you@example.com>
License-Expression: MIT
License-File: LICENSE
Requires-Python: <4.0,>=3.9
Requires-Dist: llama-index-core<0.15,>=0.13.0
Requires-Dist: llama-index-embeddings-huggingface<0.7,>=0.6.0
Requires-Dist: llama-index-utils-huggingface<0.5,>=0.4.0
Requires-Dist: optimum-intel<2,>=1.18.0
Requires-Dist: optimum[exporters]<2,>=1.16.2
